utilities/__init__.py
utilities/classutils.py
utilities/dateutils.py
utilities/decorators.py
utilities/dictutils.py
utilities/genutils.py
utilities/gitutils.py
utilities/jpegutils.py
utilities/listutils.py
utilities/mathutils.py
utilities/pathutils.py
utilities/pyplotutils.py
utilities/rwutils.py
utilities/stringutils.py
utilities/uiutils.py
utilities_dunningrb-1.0.0.dist-info/METADATA
utilities_dunningrb-1.0.0.dist-info/WHEEL
utilities_dunningrb-1.0.0.dist-info/top_level.txt
utilities_dunningrb-1.0.0.dist-info/RECORD
