Metadata-Version: 2.2
Name: utilities_dunningrb
Version: 1.0.0
Summary: A library of utility modules.
Author-email: Rodney Dunning <dunningrb@gmail.com>
License: MIT License
Project-URL: Repository, https://github.com/dunningrb/utilities
Classifier: Programming Language :: Python :: 3.8
Classifier: License :: OSI Approved :: MIT License
Classifier: Operating System :: OS Independent
Classifier: Topic :: Software Development :: Libraries :: Python Modules
Classifier: Topic :: Utilities
Requires-Python: >=3.8
